{"roomName":"tour","startTime":"Sat Jan 25 2025 16:29:23 GMT-0500","songs":[{"songNumber":1,"songInfo":{"animeNames":{"english":"Pollyanna","romaji":"Ai Shoujo Pollyanna Story"},"artist":"Mitsuko Horie","songName":"Hoshikuzu no Chandelier","type":3,"typeNumber":0,"annId":1057,"highRisk":0,"animeScore":6.33,"animeType":"TV","vintage":"Winter 1986","animeDifficulty":9.890966112368575,"animeTags":["Historical","Kids","Family Life","Female Protagonist","Foreign","Classic Literature","Rural"],"animeGenre":["Drama","Slice of Life"],"altAnimeNames":["Ai Shoujo Pollyanna Story","Pollyanna"],"altAnimeNamesAnswers":[],"siteIds":{"annId":1057,"malId":2554,"kitsuId":2319,"aniListId":2554},"rebroadcast":0,"dub":0},"correctGuess":false,"wrongGuess":true,"answer":"Santa Company","correctCount":0,"wrongCount":8,"startPoint":99,"videoLength":122.04,"videoUrl":"https://naedist.animemusicquiz.com/zovsh8.mp3","correctGuessPlayers":[],"listStates":[]},{"songNumber":2,"songInfo":{"animeNames":{"english":"Yumemiru Topo Gigio","romaji":"Yumemiru Topo Gigio"},"artist":"Satoko Yamano, Koorogi '73","songName":"Tango chu chu","type":1,"typeNumber":1,"annId":1663,"highRisk":0,"animeScore":5.37,"animeType":"TV","vintage":"Fall 1988","animeDifficulty":19.15418531152191,"animeTags":["Kids","Episodic","Animals","Anthropomorphism"],"animeGenre":["Comedy"],"altAnimeNames":["Yumemiru Topo Gigio"],"altAnimeNamesAnswers":["Topo Gigio"],"siteIds":{"annId":1663,"malId":4616,"kitsuId":3713,"aniListId":4616},"rebroadcast":0,"dub":0},"correctGuess":false,"wrongGuess":true,"answer":"Pants no Ana: Mambo de Ganbo!","correctCount":2,"wrongCount":6,"startPoint":55,"videoLength":76.32,"videoUrl":"https://naedist.animemusicquiz.com/5k4wyj.mp3","correctGuessPlayers":["I_am_stoney","FaLiLV"],"listStates":[]},{"songNumber":3,"songInfo":{"animeNames":{"english":"City Hunter 2","romaji":"City Hunter 2"},"artist":"FENCE OF DEFENSE","songName":"SARA","type":1,"typeNumber":2,"annId":484,"highRisk":0,"animeScore":8,"animeType":"TV","vintage":"Spring 1988","animeDifficulty":25.565096901824035,"animeTags":["Shounen","Slapstick","Mafia","Primarily Adult Cast","Guns","Episodic","Urban","Crime","Detective"],"animeGenre":["Comedy","Mystery"],"altAnimeNames":["City Hunter 2"],"altAnimeNamesAnswers":["Gekijouban City Hunter: Shinjuku Private Eyes"],"siteIds":{"annId":484,"malId":1471,"kitsuId":1317,"aniListId":1471},"rebroadcast":0,"dub":0},"correctGuess":false,"wrongGuess":true,"answer":"touch","correctCount":2,"wrongCount":6,"startPoint":15,"videoLength":89.424,"videoUrl":"https://naedist.animemusicquiz.com/6ig9li.mp3","correctGuessPlayers":["SUS_DOMESTICUS","FaLiLV"],"listStates":[]},{"songNumber":4,"songInfo":{"animeNames":{"english":"Moon Mask Rider","romaji":"Seigi o Ai Suru Mono Gekkou Kamen"},"artist":"Bonny Jacks","songName":"Gekkou Kamen no Uta","type":2,"typeNumber":1,"annId":2217,"highRisk":0,"animeScore":7.57,"animeType":"TV","vintage":"Winter 1972","animeDifficulty":24.041576385498047,"animeTags":["Superhero","Tokusatsu"],"animeGenre":["Action","Adventure"],"altAnimeNames":["Moon Mask Rider","Seigi o Ai Suru Mono Gekkou Kamen"],"altAnimeNamesAnswers":[],"siteIds":{"annId":2217,"malId":4332,"kitsuId":3558,"aniListId":4332},"rebroadcast":0,"dub":0},"correctGuess":false,"wrongGuess":true,"answer":"captain","correctCount":2,"wrongCount":6,"startPoint":9,"videoLength":48.672,"videoUrl":"https://naedist.animemusicquiz.com/0hytoz.mp3","correctGuessPlayers":["SUS_DOMESTICUS","FaLiLV"],"listStates":[]},{"songNumber":5,"songInfo":{"animeNames":{"english":"Detective Conan: 16 Suspects","romaji":"Meitantei Conan: 16-nin no Yougisha"},"artist":"Mai Kuraki","songName":"Winter Bells","type":2,"typeNumber":1,"annId":5141,"highRisk":0,"animeScore":6.7,"animeType":"OVA","vintage":"Winter 2002","animeDifficulty":44.96070625362739,"animeTags":["Police","Shounen","Male Protagonist","Primarily Adult Cast","Age Regression"],"animeGenre":["Adventure","Mystery"],"altAnimeNames":["Detective Conan: 16 Suspects","Meitantei Conan: 16-nin no Yougisha"],"altAnimeNamesAnswers":["Case Closed","Detective Conan","Meitantei Conan"],"siteIds":{"annId":5141,"malId":2512,"kitsuId":2278,"aniListId":2512},"rebroadcast":0,"dub":0},"correctGuess":true,"wrongGuess":false,"answer":"case closed","correctCount":7,"wrongCount":1,"startPoint":0,"videoLength":101.4,"videoUrl":"https://naedist.animemusicquiz.com/80wbgl.mp3","correctGuessPlayers":["Homebad","yasashiikumo","SUS_DOMESTICUS","MD22","I_am_stoney","Beokros","FaLiLV"],"listStates":[]},{"songNumber":6,"songInfo":{"animeNames":{"english":"Two Down Full Base","romaji":"Two Down Full Base"},"artist":"Satoko Yamano","songName":"Toshishita My Boy","type":1,"typeNumber":1,"annId":23053,"highRisk":0,"animeScore":5,"animeType":"special","vintage":"Spring 1982","animeDifficulty":13.286150754593177,"animeTags":[],"animeGenre":["Sports"],"altAnimeNames":["Two Down Full Base"],"altAnimeNamesAnswers":[],"siteIds":{"annId":23053,"malId":23537,"kitsuId":9773,"aniListId":179752},"rebroadcast":0,"dub":0},"correctGuess":false,"wrongGuess":true,"answer":"What&#39;s Michael? 2","correctCount":2,"wrongCount":6,"startPoint":58,"videoLength":94.464,"videoUrl":"https://naedist.animemusicquiz.com/yvtpuc.mp3","correctGuessPlayers":["SUS_DOMESTICUS","FaLiLV"],"listStates":[]},{"songNumber":7,"songInfo":{"animeNames":{"english":"Detective Conan","romaji":"Meitantei Conan"},"artist":"Yumi Shizukusa","songName":"I still believe~Tameiki~","type":2,"typeNumber":27,"annId":454,"highRisk":0,"animeScore":7.41,"animeType":"TV","vintage":"Winter 1996","animeDifficulty":25.583333947523585,"animeTags":["Police","School","Shounen","Male Protagonist","Tragedy","Ensemble Cast","Primarily Adult Cast","Educational","Tsundere","Episodic","Fugitive","Espionage","Conspiracy","Age Regression","Crime","Detective","Heterosexual","Primarily Teen Cast","Criminal Organization"],"animeGenre":["Adventure","Comedy","Mystery","Psychological"],"altAnimeNames":["Case Closed","Detective Conan","Meitantei Conan"],"altAnimeNamesAnswers":[],"siteIds":{"annId":454,"malId":235,"kitsuId":210,"aniListId":235},"rebroadcast":0,"dub":0},"correctGuess":true,"wrongGuess":false,"answer":"case closed","correctCount":1,"wrongCount":7,"startPoint":41,"videoLength":84.336,"videoUrl":"https://naedist.animemusicquiz.com/rcdycx.mp3","correctGuessPlayers":["MD22"],"listStates":[]},{"songNumber":8,"songInfo":{"animeNames":{"english":"Doraemon: Nobita's Great Adventure in the Antarctic Kachi Kochi","romaji":"Eiga Doraemon: Nobita no Nankyoku Kachi Kochi Daibouken"},"artist":"mao feat. Himawari Kids","songName":"Yume o Kanaete Doraemon","type":1,"typeNumber":1,"annId":19255,"highRisk":0,"animeScore":7.02,"animeType":"movie","vintage":"Winter 2017","animeDifficulty":70.84018284949268,"animeTags":["Kids","Time Manipulation","Robots","Aliens","Primarily Child Cast"],"animeGenre":["Comedy"],"altAnimeNames":["Doraemon: Nobita's Great Adventure in the Antarctic Kachi Kochi","Eiga Doraemon: Nobita no Nankyoku Kachi Kochi Daibouken"],"altAnimeNamesAnswers":["Doraemon: Nobita and the Green Giant Legend","Eiga Doraemon: Nobita to Midori no Kyojin Den","Doraemon: The Record of Nobita's Spaceblazer","Eiga Doraemon: Shin Nobita no Uchuu Kaitakushi","Doraemon","Doraemon: Nobita and the Birth of Japan 2016","Eiga Doraemon: Shin Nobita no Nippon Tanjou","Doraemon: Nobita's Chronicle of the Moon Exploration","Eiga Doraemon: Nobita no Getsumen Tansaki","Doraemon: Nobita's Secret Gadget Museum","Eiga Doraemon: Nobita no Himitsu Dougu Museum","Doraemon: New Nobita's Great Demon - Peko and the Exploration Party of Five","Eiga Doraemon: Shin Nobita no Daimakyo - Peko to 5-nin no Tankentai","Doraemon: Nobita's Great Battle of the Mermaid King","Eiga Doraemon: Nobita no Ningyo Daikaisen","Doraemon: Nobita and the New Steel Troops - Winged Angels","Eiga Doraemon: Shin Nobita to Tetsujin Heidan - Habatake Tenshi-tachi","Doraemon: Nobita and the Island of Miracles - Animal Adventure","Eiga Doraemon: Nobita to Kiseki no Shima - Animal Adventure","Doraemon"],"siteIds":{"annId":19255,"malId":33672,"kitsuId":12500,"aniListId":99085},"rebroadcast":0,"dub":0},"correctGuess":true,"wrongGuess":false,"answer":"doraemon","correctCount":8,"wrongCount":0,"startPoint":33,"videoLength":88.704,"videoUrl":"https://naedist.animemusicquiz.com/smfdfl.mp3","correctGuessPlayers":["Homebad","provenance","yasashiikumo","SUS_DOMESTICUS","MD22","I_am_stoney","Beokros","FaLiLV"],"listStates":[]},{"songNumber":9,"songInfo":{"animeNames":{"english":"Me-gumi no Daigo: Kajiba no Baka Yarou","romaji":"Me-gumi no Daigo: Kajiba no Baka Yarou"},"artist":"Hiroshi Kitadani","songName":"Red Darkness","type":2,"typeNumber":1,"annId":6961,"highRisk":0,"animeScore":6.57,"animeType":"movie","vintage":"Winter 2000","animeDifficulty":15.116513852719907,"animeTags":["Shounen","Male Protagonist","Politics","Primarily Adult Cast","Work","Urban","Firefighters"],"animeGenre":["Drama"],"altAnimeNames":["Me-gumi no Daigo: Kajiba no Baka Yarou"],"altAnimeNamesAnswers":[],"siteIds":{"annId":6961,"malId":3147,"kitsuId":2823,"aniListId":3147},"rebroadcast":0,"dub":0},"correctGuess":false,"wrongGuess":true,"answer":"Garo: Vanishing Line","correctCount":2,"wrongCount":6,"startPoint":118,"videoLength":278.304,"videoUrl":"https://naedist.animemusicquiz.com/qg11ej.mp3","correctGuessPlayers":["Beokros","FaLiLV"],"listStates":[{"name":"FaLiLV","status":2,"score":4}]},{"songNumber":10,"songInfo":{"animeNames":{"english":"Yuu☆Yuu☆Hakusho: Eizou Hakusho II","romaji":"Yuu☆Yuu☆Hakusho: Eizou Hakusho II"},"artist":"Nozomu Sasaki","songName":"TOUGH","type":3,"typeNumber":0,"annId":3349,"highRisk":0,"animeScore":6.87,"animeType":"OVA","vintage":"Fall 1995","animeDifficulty":8.130080804592225,"animeTags":["Demons","Martial Arts","Parody","Shounen","Super Power","Primarily Male Cast","Musical","Anthology","Multiple Personalities"],"animeGenre":["Action","Adventure","Comedy","Supernatural"],"altAnimeNames":["Yuu☆Yuu☆Hakusho: Eizou Hakusho II"],"altAnimeNamesAnswers":[],"siteIds":{"annId":3349,"malId":2126,"kitsuId":1923,"aniListId":2126},"rebroadcast":0,"dub":0},"correctGuess":false,"wrongGuess":true,"answer":"Ziggy Soreyuke! R&amp;R Band","correctCount":0,"wrongCount":8,"startPoint":173,"videoLength":324.024,"videoUrl":"https://naedist.animemusicquiz.com/3slsi9.mp3","correctGuessPlayers":[],"listStates":[]},{"songNumber":11,"songInfo":{"animeNames":{"english":"Les Misérables: Shoujo Cosette","romaji":"Les Misérables: Shoujo Cosette"},"artist":"Kaori Nazuka","songName":"Eien no Ring","type":3,"typeNumber":0,"annId":6912,"highRisk":0,"animeScore":7.08,"animeType":"TV","vintage":"Winter 2007","animeDifficulty":15.38588274222264,"animeTags":["Historical","Tragedy","Female Protagonist","Coming of Age","Time Skip","Bullying","Foreign","Fugitive","Classic Literature","Heterosexual","Inn"],"animeGenre":["Drama","Slice of Life"],"altAnimeNames":["Les Misérables: Shoujo Cosette"],"altAnimeNamesAnswers":[],"siteIds":{"annId":6912,"malId":1695,"kitsuId":1523,"aniListId":1695},"rebroadcast":0,"dub":0},"correctGuess":false,"wrongGuess":true,"answer":"Natsuiro Kiseki","correctCount":1,"wrongCount":7,"startPoint":60,"videoLength":129.336,"videoUrl":"https://naedist.animemusicquiz.com/u72r8o.mp3","correctGuessPlayers":["SUS_DOMESTICUS"],"listStates":[{"name":"SUS_DOMESTICUS","status":2,"score":9}]},{"songNumber":12,"songInfo":{"animeNames":{"english":"Deep Blue Town e Oide yo","romaji":"Deep Blue Town e Oide yo"},"artist":"team Umifure","songName":"DEEP BLUE TOWN e Oide yo","type":3,"typeNumber":0,"annId":23763,"highRisk":0,"animeScore":5,"animeType":"ONA","vintage":"Summer 2017","animeDifficulty":30.867535344165812,"animeTags":["Female Protagonist","Idol","No Dialogue"],"animeGenre":["Adventure","Fantasy","Slice of Life"],"altAnimeNames":["Deep Blue Town e Oide yo"],"altAnimeNamesAnswers":[],"siteIds":{"annId":23763,"malId":39313,"kitsuId":43684,"aniListId":102719},"rebroadcast":0,"dub":0},"correctGuess":true,"wrongGuess":false,"answer":"Deep Blue Town e Oide yo","correctCount":7,"wrongCount":1,"startPoint":165,"videoLength":194.088,"videoUrl":"https://naedist.animemusicquiz.com/da202p.mp3","correctGuessPlayers":["Homebad","yasashiikumo","SUS_DOMESTICUS","MD22","I_am_stoney","Beokros","FaLiLV"],"listStates":[{"name":"I_am_stoney","status":2,"score":0}]},{"songNumber":13,"songInfo":{"animeNames":{"english":"Kaibutsu-kun","romaji":"Kaibutsu-kun"},"artist":"Fuyumi Shiraishi","songName":"Ore wa Kaibutsu-kun Da","type":1,"typeNumber":1,"annId":1850,"highRisk":0,"animeScore":6.32,"animeType":"TV","vintage":"Spring 1968","animeDifficulty":38.31241996300512,"animeTags":["Demons","Shounen","Vampire","Werewolf","Achromatic"],"animeGenre":["Comedy","Horror"],"altAnimeNames":["Kaibutsu-kun"],"altAnimeNamesAnswers":[],"siteIds":{"annId":1850,"malId":3129,"kitsuId":2813,"aniListId":3129},"rebroadcast":0,"dub":0},"correctGuess":true,"wrongGuess":false,"answer":"Kaibutsu-kun","correctCount":8,"wrongCount":0,"startPoint":3,"videoLength":50.860408,"videoUrl":"https://naedist.animemusicquiz.com/f3leb8.mp3","correctGuessPlayers":["Homebad","provenance","yasashiikumo","SUS_DOMESTICUS","MD22","I_am_stoney","Beokros","FaLiLV"],"listStates":[{"name":"FaLiLV","status":5,"score":0}]},{"songNumber":14,"songInfo":{"animeNames":{"english":"City Hunter: The Secret Service","romaji":"City Hunter: The Secret Service"},"artist":"KONTA","songName":"otherwise","type":1,"typeNumber":1,"annId":551,"highRisk":0,"animeScore":7.23,"animeType":"special","vintage":"Winter 1996","animeDifficulty":12.917879248345214,"animeTags":["Police","Shounen"],"animeGenre":["Action","Comedy","Mystery"],"altAnimeNames":["City Hunter: The Secret Service"],"altAnimeNamesAnswers":[],"siteIds":{"annId":551,"malId":1477,"kitsuId":1323,"aniListId":1477},"rebroadcast":0,"dub":0},"correctGuess":false,"wrongGuess":true,"answer":"Shounan Bakusouzoku","correctCount":0,"wrongCount":8,"startPoint":41,"videoLength":92.76,"videoUrl":"https://naedist.animemusicquiz.com/35avj6.mp3","correctGuessPlayers":[],"listStates":[]},{"songNumber":15,"songInfo":{"animeNames":{"english":"Giant Robo: GinRei Special","romaji":"Giant Robo: Gaiden GinRei"},"artist":"Sumi Shimamoto","songName":"LOVE FIGHT","type":1,"typeNumber":1,"annId":3865,"highRisk":0,"animeScore":6.13,"animeType":"OVA","vintage":"Winter 1994","animeDifficulty":12.297883274354705,"animeTags":["Parody","Shounen","Super Power","Male Protagonist","Nudity","Ensemble Cast","Primarily Adult Cast","Idol","Guns","Super Robot","Episodic","Desert"],"animeGenre":["Adventure","Comedy","Mecha","Psychological","Sci-Fi"],"altAnimeNames":["Giant Robo: Gaiden GinRei","Giant Robo: GinRei Special"],"altAnimeNamesAnswers":[],"siteIds":{"annId":3865,"malId":2322,"kitsuId":2103,"aniListId":2322},"rebroadcast":0,"dub":0},"correctGuess":false,"wrongGuess":true,"answer":"Yomigaeru Sora: Rescue Wings","correctCount":1,"wrongCount":7,"startPoint":74,"videoLength":100.944,"videoUrl":"https://naedist.animemusicquiz.com/08m4hy.mp3","correctGuessPlayers":["Beokros"],"listStates":[]},{"songNumber":16,"songInfo":{"animeNames":{"english":"Sol Bianca: The Legacy","romaji":"Taiyou no Fune Sol Bianca"},"artist":"Stella Furst","songName":"TO BE FREE","type":1,"typeNumber":1,"annId":742,"highRisk":0,"animeScore":6.53,"animeType":"OVA","vintage":"Summer 1999","animeDifficulty":13.729486955915178,"animeTags":["Space","Tragedy","Primarily Female Cast","Female Protagonist","Ensemble Cast","Primarily Adult Cast","Pirates","Tanned Skin","Lost Civilisation","Artificial Intelligence","Tomboy","Travel"],"animeGenre":["Adventure","Mecha","Sci-Fi"],"altAnimeNames":["Sol Bianca: The Legacy","Taiyou no Fune Sol Bianca"],"altAnimeNamesAnswers":[],"siteIds":{"annId":742,"malId":1444,"kitsuId":1297,"aniListId":1444},"rebroadcast":0,"dub":0},"correctGuess":false,"wrongGuess":true,"answer":"all milar","correctCount":1,"wrongCount":7,"startPoint":28,"videoLength":85.392,"videoUrl":"https://naedist.animemusicquiz.com/4g38uk.mp3","correctGuessPlayers":["FaLiLV"],"listStates":[]}]}