{"roomName":"tour","startTime":"Fri Sep 05 2025 10:44:00 GMT+0200","songs":[{"songNumber":1,"songInfo":{"animeNames":{"english":"BanG Dream! 3rd Season","romaji":"BanG Dream! 3rd Season"},"artist":"Poppin'Party","composerInfo":{"artistId":10500,"name":"Noriyasu Agematsu"},"arrangerInfo":{"artistId":10505,"name":"Ryuutarou Fujinaga"},"songName":"Poppin' Shuffle","type":3,"typeNumber":0,"annId":22909,"highRisk":0,"animeScore":7.8,"animeType":"TV","vintage":"Winter 2020","animeDifficulty":28.42111795890231,"animeTags":["School","Primarily Female Cast","Full CGI","Cute Girls Doing Cute Things","Female Protagonist","Ensemble Cast","Band","Idol","Tsundere","Chuunibyou","Gyaru","Twins","Urban","Primarily Teen Cast","Rock Music"],"animeGenre":["Comedy","Music","Slice of Life"],"altAnimeNames":["BanG Dream! 3rd Season"],"altAnimeNamesAnswers":[],"siteIds":{"annId":22909,"malId":37870,"kitsuId":41290,"aniListId":101634},"rebroadcast":0,"dub":0,"seasonInfo":"Season 3"},"correctGuess":true,"wrongGuess":false,"answer":"BanG Dream! 3rd Season","correctCount":4,"wrongCount":4,"startPoint":78,"videoLength":122.351,"videoUrl":"https://eudist.animemusicquiz.com/sl2vax.webm","correctGuessPlayers":["KNotAnyMore","LiljaKatsuragi","CipherKai","Patoche49"],"listStates":[{"name":"KNotAnyMore","status":2,"score":10},{"name":"LiljaKatsuragi","status":2,"score":0},{"name":"CipherKai","status":2,"score":8},{"name":"Patoche49","status":2,"score":9},{"name":"OkitaNobu","status":2,"score":0}]},{"songNumber":2,"songInfo":{"animeNames":{"english":"Sailor Moon R","romaji":"Bishoujo Senshi Sailor Moon R"},"artist":"Sakurakko Club Sakura-gumi","composerInfo":{"artistId":1824,"name":"Akiko Kosaka"},"arrangerInfo":{"artistId":10640,"name":"Yuuzou Hayashi"},"songName":"La Soldier","type":3,"typeNumber":0,"annId":213,"highRisk":0,"animeScore":7.5,"animeType":"TV","vintage":"Winter 1993","animeDifficulty":17.98942462744662,"animeTags":["Demons","Magic","School","Shoujo","Space","Super Power","Slapstick","Tragedy","Primarily Female Cast","Time Manipulation","Female Protagonist","Henshin","Coming of Age","Ensemble Cast","War","Age Gap","Superhero","Aliens","Episodic","Reincarnation","Revenge","Rehabilitation","Urban Fantasy","Tokusatsu","Urban","Heterosexual","Primarily Teen Cast","Found Family","Unrequited Love","Parenthood"],"animeGenre":["Action","Fantasy","Mahou Shoujo","Romance","Supernatural"],"altAnimeNames":["Bishoujo Senshi Sailor Moon R","Sailor Moon R"],"altAnimeNamesAnswers":[],"siteIds":{"annId":213,"malId":740,"kitsuId":664,"aniListId":740},"rebroadcast":0,"dub":0,"seasonInfo":"Season 2"},"correctGuess":false,"wrongGuess":true,"answer":"wtf 💀","correctCount":2,"wrongCount":6,"startPoint":69,"videoLength":164.761,"videoUrl":"https://eudist.animemusicquiz.com/7i4am4.webm","correctGuessPlayers":["LiljaKatsuragi","Ephemeral"],"listStates":[{"name":"LiljaKatsuragi","status":2,"score":0}]},{"songNumber":3,"songInfo":{"animeNames":{"english":"Utagoe wa Mille-Feuille","romaji":"Utagoe wa Mille-Feuille"},"artist":"Temarizawa Koukou Acappella-bu","composerInfo":{"artistId":23326,"name":"Taiki Azegami"},"arrangerInfo":{"artistId":19526,"name":"Ryousuke Hosoi"},"songName":"Omoidebanashi","type":1,"typeNumber":1,"annId":28644,"highRisk":0,"animeScore":5.3,"animeType":"TV","vintage":"Summer 2025","animeDifficulty":34.976851851851855,"animeTags":["School","School Club","Primarily Female Cast","Female Protagonist","Coming of Age","Band","Primarily Teen Cast"],"animeGenre":["Music","Slice of Life"],"altAnimeNames":["Utagoe wa Mille-Feuille"],"altAnimeNamesAnswers":[],"siteIds":{"annId":28644,"malId":55689,"kitsuId":49901,"aniListId":166215},"rebroadcast":0,"dub":0,"seasonInfo":null},"correctGuess":true,"wrongGuess":false,"answer":"Utagoe wa Mille-Feuille","correctCount":2,"wrongCount":6,"startPoint":34,"videoLength":89.43,"videoUrl":"https://eudist.animemusicquiz.com/922s39lbxc66qvfp.webm","correctGuessPlayers":["ShelterRin","Patoche49"],"listStates":[{"name":"Patoche49","status":1,"score":0}]},{"songNumber":4,"songInfo":{"animeNames":{"english":"Nyaruko: Crawling with Love! W","romaji":"Haiyore! Nyaruko-san W"},"artist":"RAMM ni Haiyoru Mahiro-san to Yoichi-san","composerInfo":{"groupId":80023422,"name":"RAMM"},"arrangerInfo":{"groupId":80023422,"name":"RAMM"},"songName":"Ai Crusaders†Striver","type":2,"typeNumber":5,"annId":14989,"highRisk":0,"animeScore":6.9,"animeType":"TV","vintage":"Spring 2013","animeDifficulty":15.650108245481928,"animeTags":["Harem","Parody","Space","Male Protagonist","Primarily Female Cast","Love Triangle","Meta","Tsundere","Aliens","Mythology","Monster Girl","Surreal Comedy","Heterosexual"],"animeGenre":["Comedy","Romance","Sci-Fi"],"altAnimeNames":["Haiyore! Nyaruko-san W","Nyarko-san: Another Crawling Chaos W","Nyaruko: Crawling with Love! W"],"altAnimeNamesAnswers":[],"siteIds":{"annId":14989,"malId":15699,"kitsuId":7295,"aniListId":15699},"rebroadcast":0,"dub":0,"seasonInfo":"Season 2"},"correctGuess":false,"wrongGuess":true,"answer":"","correctCount":1,"wrongCount":7,"startPoint":62,"videoLength":89.013,"videoUrl":"https://eudist.animemusicquiz.com/55wv0j.webm","correctGuessPlayers":["CipherKai"],"listStates":[{"name":"ShelterRin","status":2,"score":null}]},{"songNumber":5,"songInfo":{"animeNames":{"english":"Oreimo","romaji":"Ore no Imouto ga Konnani Kawaii Wake ga Nai"},"artist":"Kana Hanazawa & Yuuichi Nakamura","composerInfo":{"artistId":17548,"name":"Neros"},"arrangerInfo":{"groupId":80025403,"name":"yamazo & Neros"},"songName":"Shokuzai no Serenade","type":2,"typeNumber":15,"annId":11512,"highRisk":0,"animeScore":6.5,"animeType":"TV","vintage":"Fall 2010","animeDifficulty":19.73414550986152,"animeTags":["Harem","Parody","School","Male Protagonist","Primarily Female Cast","Family Life","Otaku Culture","Coming of Age","Love Triangle","Tsundere","Chuunibyou","Cosplay","Writing","Urban","Kuudere","Heterosexual","Primarily Teen Cast"],"animeGenre":["Comedy","Slice of Life"],"altAnimeNames":["Ore no Imouto ga Konnani Kawaii Wake ga Nai","Oreimo"],"altAnimeNamesAnswers":[],"siteIds":{"annId":11512,"malId":8769,"kitsuId":5487,"aniListId":8769},"rebroadcast":0,"dub":0,"seasonInfo":"Season 1"},"correctGuess":true,"wrongGuess":false,"answer":"Oreimo","correctCount":6,"wrongCount":2,"startPoint":33,"videoLength":90.135,"videoUrl":"https://eudist.animemusicquiz.com/zndz26.webm","correctGuessPlayers":["KNotAnyMore","ShelterRin","LiljaKatsuragi","CipherKai","Patoche49","Ephemeral"],"listStates":[{"name":"KNotAnyMore","status":2,"score":0},{"name":"ShelterRin","status":2,"score":null},{"name":"LiljaKatsuragi","status":2,"score":8},{"name":"CipherKai","status":2,"score":2},{"name":"Ephemeral","status":2,"score":7}]},{"songNumber":6,"songInfo":{"animeNames":{"english":"One Week Friends","romaji":"Isshuukan Friends."},"artist":"Sora Amamiya","composerInfo":{"groupId":80022901,"name":"Takuya Ohashi & Shintarou Tokita"},"arrangerInfo":{"artistId":9204,"name":"Ruka Kawada"},"songName":"Kanade","type":2,"typeNumber":1,"annId":15721,"highRisk":0,"animeScore":7.3,"animeType":"TV","vintage":"Spring 2014","animeDifficulty":30.48076923076923,"animeTags":["School","Amnesia","Rehabilitation","Heterosexual","Primarily Teen Cast"],"animeGenre":["Comedy","Drama","Romance","Slice of Life"],"altAnimeNames":["Isshuukan Friends.","One Week Friends"],"altAnimeNamesAnswers":[],"siteIds":{"annId":15721,"malId":21327,"kitsuId":8096,"aniListId":20527},"rebroadcast":0,"dub":0,"seasonInfo":null},"correctGuess":false,"wrongGuess":true,"answer":"Sword Art Online II","correctCount":4,"wrongCount":4,"startPoint":61,"videoLength":107.614,"videoUrl":"https://eudist.animemusicquiz.com/yt4lao.webm","correctGuessPlayers":["KNotAnyMore","ShelterRin","CipherKai","Ephemeral"],"listStates":[{"name":"KNotAnyMore","status":2,"score":8},{"name":"ShelterRin","status":2,"score":null},{"name":"Ephemeral","status":2,"score":8}]},{"songNumber":7,"songInfo":{"animeNames":{"english":"Revue Starlight","romaji":"Shoujo☆Kageki Revue Starlight"},"artist":"Momoyo Koyama & Suzuko Mimori","composerInfo":{"groupId":80023822,"name":"Yoshiaki Fujisawa & Tatsuya Katou"},"arrangerInfo":{"groupId":80023822,"name":"Yoshiaki Fujisawa & Tatsuya Katou"},"songName":"Starlight","type":3,"typeNumber":0,"annId":20891,"highRisk":1,"animeScore":7.7,"animeType":"TV","vintage":"Summer 2018","animeDifficulty":29.535378855921703,"animeTags":["Swordplay","School","Yuri","Primarily Female Cast","Cute Girls Doing Cute Things","Female Protagonist","Henshin","Battle Royale","Coming of Age","Ensemble Cast","Love Triangle","Meta","Dancing","Musical","Philosophy","Fairy Tale","Animals","LGBTQ Issues","Acting","Primarily Teen Cast","Spearplay","Boarding School","Unrequited Love","Time Loop"],"animeGenre":["Action","Drama","Music","Psychological"],"altAnimeNames":["Revue Starlight","Shoujo☆Kageki Revue Starlight"],"altAnimeNamesAnswers":["Revue Starlight: Rondo Rondo Rondo","Shoujo☆Kageki Revue Starlight: Rondo Rondo Rondo"],"siteIds":{"annId":20891,"malId":35503,"kitsuId":14174,"aniListId":98658},"rebroadcast":0,"dub":0,"seasonInfo":"TV"},"correctGuess":false,"wrongGuess":true,"answer":"Healer Girl","correctCount":2,"wrongCount":6,"startPoint":230,"videoLength":424.234,"videoUrl":"https://eudist.animemusicquiz.com/h1ki3f.webm","correctGuessPlayers":["KNotAnyMore","CipherKai"],"listStates":[{"name":"ShelterRin","status":2,"score":null},{"name":"CipherKai","status":2,"score":8},{"name":"OkitaNobu","status":2,"score":0}]},{"songNumber":8,"songInfo":{"animeNames":{"english":"Hensuki: Are You Willing to Fall in Love With a Pervert, As Long As She's a Cutie?","romaji":"Kawaikereba Hentai demo Suki ni Natte Kuremasu ka?"},"artist":"Mia REGINA","composerInfo":{"groupId":80023279,"name":"halu-note & Takayuki Oota"},"arrangerInfo":{"groupId":80023279,"name":"halu-note & Takayuki Oota"},"songName":"Mubyuu no Hana","type":2,"typeNumber":1,"annId":22018,"highRisk":0,"animeScore":6.2,"animeType":"TV","vintage":"Summer 2019","animeDifficulty":24.372081751626897,"animeTags":["Harem","Parody","School","Male Protagonist","School Club","Primarily Female Cast","Meta","Tsundere","Detective","Heterosexual"],"animeGenre":["Comedy","Ecchi","Mystery","Romance"],"altAnimeNames":["Hensuki: Are You Willing to Fall in Love With a Pervert, As Long As She's a Cutie?","Kawaikereba Hentai demo Suki ni Natte Kuremasu ka?"],"altAnimeNamesAnswers":[],"siteIds":{"annId":22018,"malId":39326,"kitsuId":42211,"aniListId":107961},"rebroadcast":0,"dub":0,"seasonInfo":null},"correctGuess":false,"wrongGuess":true,"answer":"rahhhhh brain ","correctCount":4,"wrongCount":4,"startPoint":27,"videoLength":88.387,"videoUrl":"https://eudist.animemusicquiz.com/fn4eei.webm","correctGuessPlayers":["KNotAnyMore","FoopyPoopy","LiljaKatsuragi","Ephemeral"],"listStates":[{"name":"KNotAnyMore","status":2,"score":6},{"name":"FoopyPoopy","status":2,"score":6},{"name":"LiljaKatsuragi","status":2,"score":6},{"name":"Ephemeral","status":2,"score":7}]},{"songNumber":9,"songInfo":{"animeNames":{"english":"Sasaki and Peeps","romaji":"Sasaki to Pi-chan"},"artist":"Aguri Oonishi","composerInfo":{"groupId":80023919,"name":"Hitomi Sano & Toshiya Watanabe"},"arrangerInfo":{"artistId":19530,"name":"Toshiya Watanabe"},"songName":"Aimai Girl","type":2,"typeNumber":1,"annId":26120,"highRisk":0,"animeScore":6.7,"animeType":"TV","vintage":"Winter 2024","animeDifficulty":31.788294479068675,"animeTags":["Magic","Police","Super Power","Male Protagonist","Age Gap","Work","Guns","Crossover","Reincarnation","Isekai","Economics","Urban Fantasy","Animals"],"animeGenre":["Comedy","Fantasy"],"altAnimeNames":["Sasaki and Peeps","Sasaki to Pi-chan"],"altAnimeNamesAnswers":[],"siteIds":{"annId":26120,"malId":52482,"kitsuId":46303,"aniListId":152682},"rebroadcast":0,"dub":0,"seasonInfo":null},"correctGuess":false,"wrongGuess":true,"answer":"The iDOLM@STER Cinderella Girls U149","correctCount":0,"wrongCount":8,"startPoint":62,"videoLength":88.185,"videoUrl":"https://eudist.animemusicquiz.com/ynrvuc.webm","correctGuessPlayers":[],"listStates":[{"name":"CipherKai","status":2,"score":5},{"name":"OkitaNobu","status":2,"score":0}]},{"songNumber":10,"songInfo":{"animeNames":{"english":"Kokoro Connect","romaji":"Kokoro Connect"},"artist":"Team.Nekokan [Neko] featuring. Junca Amaoto","composerInfo":{"artistId":14585,"name":"nyanyannya"},"arrangerInfo":{"groupId":80026716,"name":"Team.Nekokan [Neko]"},"songName":"Kokoro no Kara","type":2,"typeNumber":1,"annId":14113,"highRisk":0,"animeScore":7.5,"animeType":"TV","vintage":"Summer 2012","animeDifficulty":20.966304467429577,"animeTags":["School","Gender Bending","Male Protagonist","School Club","Primarily Female Cast","Female Protagonist","Coming of Age","Ensemble Cast","Love Triangle","Body Swapping","Tsundere","Urban Fantasy","Philosophy","Age Regression","Heterosexual"],"animeGenre":["Drama","Romance","Slice of Life","Supernatural"],"altAnimeNames":["Kokoro Connect"],"altAnimeNamesAnswers":[],"siteIds":{"annId":14113,"malId":11887,"kitsuId":6626,"aniListId":11887},"rebroadcast":0,"dub":0,"seasonInfo":null},"correctGuess":true,"wrongGuess":false,"answer":"Kokoro Connect","correctCount":4,"wrongCount":4,"startPoint":5,"videoLength":104.026,"videoUrl":"https://eudist.animemusicquiz.com/fisyun.webm","correctGuessPlayers":["ShelterRin","CipherKai","Patoche49","Ephemeral"],"listStates":[{"name":"ShelterRin","status":2,"score":null},{"name":"CipherKai","status":2,"score":8},{"name":"Patoche49","status":2,"score":8},{"name":"OkitaNobu","status":2,"score":0}]},{"songNumber":11,"songInfo":{"animeNames":{"english":"Kubo Won't Let Me Be Invisible","romaji":"Kubo-san wa Mob o Yurusanai"},"artist":"Kana Hanazawa","composerInfo":{"artistId":10960,"name":"Katsutoshi Kitagawa"},"arrangerInfo":{"groupId":80025487,"name":"Katsutoshi Kitagawa, Dan Miyakawa, Tansa"},"songName":"Dramatic ja Nakute mo","type":1,"typeNumber":1,"annId":25694,"highRisk":0,"animeScore":7.5,"animeType":"TV","vintage":"Winter 2023","animeDifficulty":38.78333297635367,"animeTags":["School","Iyashikei","Male Protagonist","Episodic","Chibi","Heterosexual","Primarily Teen Cast"],"animeGenre":["Comedy","Romance","Slice of Life"],"altAnimeNames":["Kubo Won't Let Me Be Invisible","Kubo-san wa Mob o Yurusanai"],"altAnimeNamesAnswers":[],"siteIds":{"annId":25694,"malId":51815,"kitsuId":46110,"aniListId":148969},"rebroadcast":0,"dub":0,"seasonInfo":null},"correctGuess":true,"wrongGuess":false,"answer":"Kubo Won&#39;t Let Me Be Invisible","correctCount":5,"wrongCount":3,"startPoint":24,"videoLength":89.008,"videoUrl":"https://eudist.animemusicquiz.com/h08yjj.webm","correctGuessPlayers":["KNotAnyMore","ShelterRin","LiljaKatsuragi","CipherKai","Patoche49"],"listStates":[{"name":"KNotAnyMore","status":2,"score":10},{"name":"CipherKai","status":2,"score":7}]},{"songNumber":12,"songInfo":{"animeNames":{"english":"How Heavy Are the Dumbbells You Lift?","romaji":"Dumbbell Nan-Kilo Moteru?"},"artist":"tea","composerInfo":{"artistId":20984,"name":"tea"},"arrangerInfo":{"artistId":20984,"name":"tea"},"songName":"Snow Globe","type":2,"typeNumber":2,"annId":21764,"highRisk":0,"animeScore":7.1,"animeType":"TV","vintage":"Summer 2019","animeDifficulty":18.7726904739426,"animeTags":["Parody","Shounen","Primarily Female Cast","Cute Girls Doing Cute Things","Female Protagonist","Nudity","Educational","Food","Meta","Teacher","Boxing","Fitness","Episodic","Athletics","Tanned Skin","Gyaru","Urban","Tomboy"],"animeGenre":["Comedy","Ecchi","Slice of Life","Sports"],"altAnimeNames":["Dumbbell Nan-Kilo Moteru?","How Heavy Are the Dumbbells You Lift?"],"altAnimeNamesAnswers":[],"siteIds":{"annId":21764,"malId":39026,"kitsuId":42134,"aniListId":107226},"rebroadcast":0,"dub":0,"seasonInfo":null},"correctGuess":true,"wrongGuess":false,"answer":"Dumbbell Nan-Kilo Moteru?","correctCount":1,"wrongCount":7,"startPoint":1,"videoLength":199.366,"videoUrl":"https://eudist.animemusicquiz.com/q43ljd.webm","correctGuessPlayers":["Patoche49"],"listStates":[{"name":"FoopyPoopy","status":2,"score":8},{"name":"Patoche49","status":2,"score":0}]},{"songNumber":13,"songInfo":{"animeNames":{"english":"The Idol Master","romaji":"The iDOLM@STER"},"artist":"Asami Imai","composerInfo":{"artistId":5697,"name":"Go Shiina"},"arrangerInfo":{"artistId":5697,"name":"Go Shiina"},"songName":"Nemuri Hime","type":3,"typeNumber":0,"annId":12436,"highRisk":0,"animeScore":7.5,"animeType":"TV","vintage":"Summer 2011","animeDifficulty":31.89794344290264,"animeTags":["Primarily Female Cast","Cute Girls Doing Cute Things","Ensemble Cast","Idol","Work","Tsundere","Dancing","Twins","Found Family"],"animeGenre":["Comedy","Drama","Music","Slice of Life"],"altAnimeNames":["The Idol Master","The iDOLM@STER"],"altAnimeNamesAnswers":["The iDOLM@STER Movie: Beyond the Brilliant Future!","The iDOLM@STER Movie: Kagayaki no Mukougawa e!"],"siteIds":{"annId":12436,"malId":10278,"kitsuId":6111,"aniListId":10278},"rebroadcast":0,"dub":0,"seasonInfo":"TV 2"},"correctGuess":false,"wrongGuess":true,"answer":"","correctCount":2,"wrongCount":6,"startPoint":76,"videoLength":153.507,"videoUrl":"https://eudist.animemusicquiz.com/dxp7sc.webm","correctGuessPlayers":["ShelterRin","Ephemeral"],"listStates":[{"name":"KNotAnyMore","status":2,"score":8},{"name":"ShelterRin","status":2,"score":null}]},{"songNumber":14,"songInfo":{"animeNames":{"english":"Arpeggio of Blue Steel: Ars Nova - Cadenza","romaji":"Aoki Hagane no Arpeggio: Ars Nova Cadenza"},"artist":"nano","composerInfo":{"artistId":14852,"name":"WEST GROUND"},"arrangerInfo":{"artistId":15490,"name":"Natsumi Kameoka"},"songName":"Last Refrain","type":3,"typeNumber":0,"annId":16741,"highRisk":0,"animeScore":7.5,"animeType":"movie","vintage":"Fall 2015","animeDifficulty":20.361688117878685,"animeTags":["Full CGI","Ships"],"animeGenre":["Action","Drama","Sci-Fi"],"altAnimeNames":["Aoki Hagane no Arpeggio: Ars Nova Cadenza","Arpeggio of Blue Steel: Ars Nova - Cadenza"],"altAnimeNamesAnswers":[],"siteIds":{"annId":16741,"malId":24921,"kitsuId":8788,"aniListId":20764},"rebroadcast":0,"dub":0,"seasonInfo":"Movie 2"},"correctGuess":false,"wrongGuess":true,"answer":"The iDOLM@STER Shiny Colors","correctCount":2,"wrongCount":6,"startPoint":202,"videoLength":282.372,"videoUrl":"https://eudist.animemusicquiz.com/axbybf.webm","correctGuessPlayers":["LiljaKatsuragi","Ephemeral"],"listStates":[{"name":"CipherKai","status":2,"score":5},{"name":"Ephemeral","status":2,"score":9}]},{"songNumber":15,"songInfo":{"animeNames":{"english":"Bamboo Blade","romaji":"Bamboo Blade"},"artist":"Shinichi Ishihara","composerInfo":{"artistId":3659,"name":"Kotaro Nakagawa"},"arrangerInfo":{"artistId":3659,"name":"Kotaro Nakagawa"},"songName":"Shinaider no Uta","type":3,"typeNumber":0,"annId":8455,"highRisk":0,"animeScore":7.2,"animeType":"TV","vintage":"Fall 2007","animeDifficulty":26.417581644144143,"animeTags":["Martial Arts","School","School Club","Primarily Female Cast","Coming of Age","Athletics"],"animeGenre":["Comedy","Sports"],"altAnimeNames":["Bamboo Blade"],"altAnimeNamesAnswers":[],"siteIds":{"annId":8455,"malId":2986,"kitsuId":2700,"aniListId":2986},"rebroadcast":0,"dub":0,"seasonInfo":null},"correctGuess":false,"wrongGuess":true,"answer":"Detective Conan: The Culprit Hanzawa","correctCount":2,"wrongCount":6,"startPoint":6,"videoLength":30.064,"videoUrl":"https://eudist.animemusicquiz.com/1bayhy.webm","correctGuessPlayers":["KNotAnyMore","LiljaKatsuragi"],"listStates":[{"name":"KNotAnyMore","status":2,"score":7},{"name":"LiljaKatsuragi","status":1,"score":0}]},{"songNumber":16,"songInfo":{"animeNames":{"english":"Infinite Dendrogram","romaji":"Infinite Dendrogram"},"artist":"Aya Uchida","composerInfo":{"artistId":10424,"name":"Katsuhiko Kurosu"},"arrangerInfo":{"artistId":10424,"name":"Katsuhiko Kurosu"},"songName":"Reverb","type":2,"typeNumber":1,"annId":21768,"highRisk":0,"animeScore":5.9,"animeType":"TV","vintage":"Winter 2020","animeDifficulty":21.91502964228296,"animeTags":["Magic","Male Protagonist","Gore","Virtual World","Real Robot","Crossdressing","Isekai","Video Games","Artificial Intelligence","Shapeshifting","Chimera"],"animeGenre":["Action","Adventure","Fantasy"],"altAnimeNames":["Infinite Dendrogram"],"altAnimeNamesAnswers":[],"siteIds":{"annId":21768,"malId":38909,"kitsuId":42131,"aniListId":107420},"rebroadcast":0,"dub":0,"seasonInfo":null},"correctGuess":false,"wrongGuess":true,"answer":"","correctCount":2,"wrongCount":6,"startPoint":43,"videoLength":89.757,"videoUrl":"https://eudist.animemusicquiz.com/jn62tf.webm","correctGuessPlayers":["OkitaNobu","Ephemeral"],"listStates":[{"name":"FoopyPoopy","status":2,"score":6},{"name":"OkitaNobu","status":2,"score":0}]},{"songNumber":17,"songInfo":{"animeNames":{"english":"Yuki Yuna is A Hero: Great Mankai Chapter","romaji":"Yuuki Yuuna wa Yuusha de Aru: Dai Mankai no Shou"},"artist":"Sanshuu Chuugaku Yuusha-bu","composerInfo":{"artistId":13494,"name":"Keiichi Okabe"},"arrangerInfo":{"artistId":13494,"name":"Keiichi Okabe"},"songName":"Chiheisen no Mukou e","type":2,"typeNumber":1,"annId":23555,"highRisk":0,"animeScore":7.3,"animeType":"TV","vintage":"Fall 2021","animeDifficulty":22.081232196147585,"animeTags":["Magic","Swordplay","School","School Club","Tragedy","Primarily Female Cast","CGI","Cute Girls Doing Cute Things","Post-Apocalyptic","Gore","Female Protagonist","Henshin","Ensemble Cast","Time Skip","Yandere","Tsundere","Superhero","Isekai","Gods","Kaiju","Ships","Urban Fantasy","Primarily Child Cast","Miko","Urban","Religion","Spearplay","Fairy","Camping"],"animeGenre":["Action","Drama","Fantasy","Mahou Shoujo","Psychological"],"altAnimeNames":["Yuki Yuna is A Hero: Great Mankai Chapter","Yuuki Yuuna wa Yuusha de Aru: Dai Mankai no Shou"],"altAnimeNamesAnswers":[],"siteIds":{"annId":23555,"malId":42587,"kitsuId":44333,"aniListId":122292},"rebroadcast":0,"dub":0,"seasonInfo":"Season 4"},"correctGuess":false,"wrongGuess":true,"answer":"hummmm","correctCount":2,"wrongCount":6,"startPoint":20,"videoLength":87.387,"videoUrl":"https://eudist.animemusicquiz.com/badyai.webm","correctGuessPlayers":["ShelterRin","CipherKai"],"listStates":[{"name":"ShelterRin","status":2,"score":null}]},{"songNumber":18,"songInfo":{"animeNames":{"english":"Beyond the Boundary Idol Trial!: They Who Judge You Even Though They Waver","romaji":"Kyoukai no Kanata: Idol Saiban! - Mayoi Nagara mo Kimi o Sabaku Tami"},"artist":"Yuri Yamaoka, Risa Taneda, Minori Chihara, Moe Toyota","composerInfo":{"artistId":5277,"name":"ZAQ"},"arrangerInfo":{"artistId":5277,"name":"ZAQ"},"songName":"Judgment ja!","type":3,"typeNumber":0,"annId":15748,"highRisk":0,"animeScore":6.2,"animeType":"ONA","vintage":"Fall 2013","animeDifficulty":30.064612214129074,"animeTags":["Primarily Female Cast","Cute Girls Doing Cute Things","Female Protagonist","Idol","Chibi"],"animeGenre":["Comedy"],"altAnimeNames":["Beyond the Boundary Idol Trial!: They Who Judge You Even Though They Waver","Kyoukai no Kanata: Idol Saiban! - Mayoi Nagara mo Kimi o Sabaku Tami"],"altAnimeNamesAnswers":[],"siteIds":{"annId":15748,"malId":21241,"kitsuId":8086,"aniListId":20524},"rebroadcast":0,"dub":0,"seasonInfo":"ONA"},"correctGuess":true,"wrongGuess":false,"answer":"Kyoukai no Kanata: Idol Saiban! - Mayoi Nagara mo Kimi o Sabaku Tami","correctCount":4,"wrongCount":4,"startPoint":2,"videoLength":34.368,"videoUrl":"https://eudist.animemusicquiz.com/cxdnsv.webm","correctGuessPlayers":["KNotAnyMore","CipherKai","Patoche49","Ephemeral"],"listStates":[{"name":"Patoche49","status":2,"score":0}]},{"songNumber":19,"songInfo":{"animeNames":{"english":"Smile Down the Runway","romaji":"Runway de Waratte"},"artist":"MIWA BRAVEBIRD & gb","composerInfo":{"artistId":16137,"name":"Akinari Suzuki"},"arrangerInfo":{"artistId":16137,"name":"Akinari Suzuki"},"songName":"Bring me back","type":3,"typeNumber":0,"annId":22516,"highRisk":0,"animeScore":7.3,"animeType":"TV","vintage":"Winter 2020","animeDifficulty":17.354206751099458,"animeTags":["Shounen","Male Protagonist","Family Life","Female Protagonist","Coming of Age","Work","Fashion"],"animeGenre":["Drama","Slice of Life"],"altAnimeNames":["Runway de Waratte","Smile Down the Runway"],"altAnimeNamesAnswers":[],"siteIds":{"annId":22516,"malId":40392,"kitsuId":42552,"aniListId":111501},"rebroadcast":0,"dub":0,"seasonInfo":null},"correctGuess":false,"wrongGuess":true,"answer":"","correctCount":2,"wrongCount":6,"startPoint":9,"videoLength":80.998,"videoUrl":"https://eudist.animemusicquiz.com/f52vnc.webm","correctGuessPlayers":["LiljaKatsuragi","Ephemeral"],"listStates":[{"name":"LiljaKatsuragi","status":2,"score":8}]},{"songNumber":20,"songInfo":{"animeNames":{"english":"Steins;Gate 0","romaji":"Steins;Gate 0"},"artist":"Eri Sasaki","composerInfo":{"artistId":15801,"name":"Takeshi Abo"},"arrangerInfo":{"artistId":14415,"name":"Shinichi Yuki"},"songName":"GATE OF STEINER","type":2,"typeNumber":6,"annId":20446,"highRisk":1,"animeScore":8.4,"animeType":"TV","vintage":"Spring 2018","animeDifficulty":34.80440553477113,"animeTags":["Military","Male Protagonist","Tragedy","Post-Apocalyptic","Time Manipulation","Otaku Culture","War","Alternate Universe","Time Skip","Dystopian","Fugitive","Amnesia","Chuunibyou","Memory Manipulation","Philosophy","College","Age Regression","Artificial Intelligence","Multiple Personalities","Urban","Denpa","Kuudere"],"animeGenre":["Drama","Psychological","Sci-Fi","Thriller"],"altAnimeNames":["Steins;Gate 0"],"altAnimeNamesAnswers":[],"siteIds":{"annId":20446,"malId":30484,"kitsuId":10788,"aniListId":21127},"rebroadcast":0,"dub":0,"seasonInfo":"Season 2"},"correctGuess":true,"wrongGuess":false,"answer":"Steins;Gate 0","correctCount":4,"wrongCount":4,"startPoint":155,"videoLength":245.961,"videoUrl":"https://eudist.animemusicquiz.com/jg4h2n.webm","correctGuessPlayers":["ShelterRin","LiljaKatsuragi","Patoche49","Ephemeral"],"listStates":[{"name":"ShelterRin","status":2,"score":null},{"name":"LiljaKatsuragi","status":2,"score":9},{"name":"CipherKai","status":2,"score":9},{"name":"Ephemeral","status":2,"score":10}]},{"songNumber":21,"songInfo":{"animeNames":{"english":"ReLIFE","romaji":"ReLIFE"},"artist":"L'Arc~en~Ciel","composerInfo":{"artistId":21713,"name":"hyde"},"arrangerInfo":{"groupId":80027006,"name":"L'Arc~en~Ciel & Hajime Okano"},"songName":"HONEY","type":2,"typeNumber":4,"annId":16917,"highRisk":0,"animeScore":7.8,"animeType":"TV","vintage":"Summer 2016","animeDifficulty":20.834406355495123,"animeTags":["School","Seinen","Male Protagonist","Slapstick","Tragedy","Time Manipulation","Coming of Age","Age Gap","Work","Hikikomori","Rehabilitation","Chibi","Memory Manipulation","Age Regression","Kuudere","Heterosexual","Primarily Teen Cast"],"animeGenre":["Comedy","Drama","Romance","Slice of Life"],"altAnimeNames":["ReLIFE"],"altAnimeNamesAnswers":[],"siteIds":{"annId":16917,"malId":30015,"kitsuId":10464,"aniListId":21049},"rebroadcast":0,"dub":0,"seasonInfo":"TV 2016"},"correctGuess":true,"wrongGuess":false,"answer":"ReLIFE","correctCount":3,"wrongCount":5,"startPoint":18,"videoLength":93.322,"videoUrl":"https://eudist.animemusicquiz.com/d51xnm.webm","correctGuessPlayers":["LiljaKatsuragi","Patoche49","Ephemeral"],"listStates":[{"name":"LiljaKatsuragi","status":2,"score":7},{"name":"Patoche49","status":2,"score":0},{"name":"Ephemeral","status":2,"score":9}]},{"songNumber":22,"songInfo":{"animeNames":{"english":"Gonna be the Twin-Tail!!","romaji":"Ore, Twintail ni Narimasu."},"artist":"Yoko Hikasa","composerInfo":{"artistId":15191,"name":"Fuwari P"},"arrangerInfo":{"artistId":15191,"name":"Fuwari P"},"songName":"Koi no Megane","type":3,"typeNumber":0,"annId":16132,"highRisk":0,"animeScore":6.1,"animeType":"TV","vintage":"Fall 2014","animeDifficulty":36.2424653995491,"animeTags":["School","Super Power","Gender Bending","Satire","Male Protagonist","Primarily Female Cast","Otaku Culture","Henshin","Tsundere","Superhero","Tokusatsu"],"animeGenre":["Action","Comedy","Ecchi","Fantasy","Romance"],"altAnimeNames":["Gonna be the Twin-Tail!!","Ore, Twintail ni Narimasu."],"altAnimeNamesAnswers":[],"siteIds":{"annId":16132,"malId":24705,"kitsuId":8710,"aniListId":20565},"rebroadcast":0,"dub":0,"seasonInfo":null},"correctGuess":false,"wrongGuess":true,"answer":"","correctCount":5,"wrongCount":3,"startPoint":12,"videoLength":56.041,"videoUrl":"https://eudist.animemusicquiz.com/1m253s.webm","correctGuessPlayers":["KNotAnyMore","ShelterRin","LiljaKatsuragi","CipherKai","Ephemeral"],"listStates":[{"name":"CipherKai","status":2,"score":4},{"name":"Ephemeral","status":2,"score":7}]},{"songNumber":23,"songInfo":{"animeNames":{"english":"Arpeggio of Blue Steel: Ars Nova - DC","romaji":"Aoki Hagane no Arpeggio: Ars Nova DC"},"artist":"Trident","composerInfo":{"groupId":80026225,"name":"Heart's Cry"},"arrangerInfo":{"groupId":80026225,"name":"Heart's Cry"},"songName":"Blue Snow","type":1,"typeNumber":1,"annId":16333,"highRisk":0,"animeScore":7.1,"animeType":"movie","vintage":"Winter 2015","animeDifficulty":21.444723038545654,"animeTags":["Military","Full CGI","Ships"],"animeGenre":["Action","Sci-Fi"],"altAnimeNames":["Aoki Hagane no Arpeggio: Ars Nova DC","Arpeggio of Blue Steel: Ars Nova - DC"],"altAnimeNamesAnswers":[],"siteIds":{"annId":16333,"malId":24919,"kitsuId":8787,"aniListId":20763},"rebroadcast":0,"dub":0,"seasonInfo":"Movie 1"},"correctGuess":false,"wrongGuess":true,"answer":"","correctCount":1,"wrongCount":7,"startPoint":112,"videoLength":162.079,"videoUrl":"https://eudist.animemusicquiz.com/a0mg5s.webm","correctGuessPlayers":["Ephemeral"],"listStates":[{"name":"CipherKai","status":2,"score":5},{"name":"Ephemeral","status":2,"score":9}]},{"songNumber":24,"songInfo":{"animeNames":{"english":"BOFURI: I Don't Want to Get Hurt, so I'll Max Out My Defense. Season 2","romaji":"Itai no wa Iya nanode Bougyoryoku ni Kyokufuri Shitai to Omoimasu. 2"},"artist":"FRAM","composerInfo":{"groupId":80026398,"name":"amazuti"},"arrangerInfo":{"groupId":80026398,"name":"amazuti"},"songName":"Step for Joy","type":2,"typeNumber":1,"annId":23894,"highRisk":0,"animeScore":7.1,"animeType":"TV","vintage":"Winter 2023","animeDifficulty":28.051228326081223,"animeTags":["Magic","Primarily Female Cast","CGI","Cute Girls Doing Cute Things","Female Protagonist","Henshin","Ensemble Cast","Virtual World","Monster Girl","Video Games","Animals","Twins","Dungeon","Shapeshifting","Primarily Teen Cast"],"animeGenre":["Action","Adventure","Comedy","Fantasy","Slice of Life"],"altAnimeNames":["BOFURI: I Don't Want to Get Hurt, so I'll Max Out My Defense. Season 2","Itai no wa Iya nanode Bougyoryoku ni Kyokufuri Shitai to Omoimasu. 2"],"altAnimeNamesAnswers":[],"siteIds":{"annId":23894,"malId":41514,"kitsuId":43086,"aniListId":116867},"rebroadcast":0,"dub":0,"seasonInfo":"Season 2"},"correctGuess":false,"wrongGuess":true,"answer":"","correctCount":4,"wrongCount":4,"startPoint":32,"videoLength":89.013,"videoUrl":"https://eudist.animemusicquiz.com/w56v1k.webm","correctGuessPlayers":["KNotAnyMore","FoopyPoopy","LiljaKatsuragi","CipherKai"],"listStates":[{"name":"KNotAnyMore","status":2,"score":8},{"name":"FoopyPoopy","status":2,"score":6},{"name":"CipherKai","status":2,"score":7}]},{"songNumber":25,"songInfo":{"animeNames":{"english":"Pokémon: The First Movie","romaji":"Pocket Monsters: Mewtwo no Gyakushuu"},"artist":"Sachiko Kobayashi","composerInfo":{"artistId":2483,"name":"Hirokazu Tanaka"},"arrangerInfo":{"artistId":4302,"name":"Kan Sawada"},"songName":"Kaze to Issho ni","type":2,"typeNumber":1,"annId":196,"highRisk":0,"animeScore":7.4,"animeType":"movie","vintage":"Summer 1998","animeDifficulty":19.01232513537906,"animeTags":["Kids","Male Protagonist","Tragedy","CGI","Anti-Hero","Memory Manipulation","Philosophy","Delinquents","Animals","Primarily Child Cast","Clone","Proxy Battle"],"animeGenre":["Action","Adventure","Drama","Fantasy","Sci-Fi"],"altAnimeNames":["Pocket Monsters: Mewtwo no Gyakushuu","Pokémon: The First Movie"],"altAnimeNamesAnswers":["Pocket Monsters: Diamond & Pearl","Pokémon: Diamond and Pearl","Pocket Monsters","Pokémon"],"siteIds":{"annId":196,"malId":528,"kitsuId":487,"aniListId":528},"rebroadcast":0,"dub":0,"seasonInfo":"Movie 1"},"correctGuess":true,"wrongGuess":false,"answer":"Pokémon: The First Movie","correctCount":5,"wrongCount":3,"startPoint":212,"videoLength":243.584,"videoUrl":"https://eudist.animemusicquiz.com/yikkw2.webm","correctGuessPlayers":["KNotAnyMore","ShelterRin","CipherKai","Patoche49","Ephemeral"],"listStates":[{"name":"LiljaKatsuragi","status":2,"score":7},{"name":"CipherKai","status":2,"score":7},{"name":"Patoche49","status":2,"score":8}]}]}